matlablib.py
matlablib-1.3.dist-info/LICENSE.txt
matlablib-1.3.dist-info/METADATA
matlablib-1.3.dist-info/WHEEL
matlablib-1.3.dist-info/top_level.txt
matlablib-1.3.dist-info/RECORD
