Metadata-Version: 2.1
Name: matlablib
Version: 1.3
Summary: Matlab-tool suite
Home-page: https://github.com/OSHI7/matlablib
Author: Josh Philipson
Author-email: philipson@gmail.com
License: MIT
Platform: UNKNOWN
Classifier: Programming Language :: Python :: 3
Classifier: Programming Language :: Python :: 3.6
Classifier: Programming Language :: Python :: 3.7
Classifier: Programming Language :: Python :: 3.8
Classifier: License :: OSI Approved :: MIT License
Classifier: Operating System :: OS Independent
